<annotation>
  <filename>40001.jpg</filename>
  <size>
    <width>1920</width>
    <height>1080</height>
    <depth>3</depth>
  </size>
  <object>
    <name>person</name>
    <pose>Unspecified</pose>
    <truncated>0</truncated>
    <difficult>0</difficult>
    <bnbbox>
      <xmin>224</xmin>
      <ymin>118</ymin>
      <xmax>270</xmax>
      <ymax>286</ymax>
    </bnbbox>
  </object>
  <object>
    <name>person</name>
    <pose>Unspecified</pose>
    <truncated>0</truncated>
    <difficult>0</difficult>
    <bnbbox>
      <xmin>111</xmin>
      <ymin>536</ymin>
      <xmax>186</xmax>
      <ymax>803</ymax>
    </bnbbox>
  </object>
  <object>
    <name>person</name>
    <pose>Unspecified</pose>
    <truncated>0</truncated>
    <difficult>0</difficult>
    <bnbbox>
      <xmin>709</xmin>
      <ymin>-3</ymin>
      <xmax>761</xmax>
      <ymax>154</ymax>
    </bnbbox>
  </object>
  <object>
    <name>person</name>
    <pose>Unspecified</pose>
    <truncated>0</truncated>
    <difficult>0</difficult>
    <bnbbox>
      <xmin>1039</xmin>
      <ymin>133</ymin>
      <xmax>1116</xmax>
      <ymax>313</ymax>
    </bnbbox>
  </object>
  <object>
    <name>person</name>
    <pose>Unspecified</pose>
    <truncated>0</truncated>
    <difficult>0</difficult>
    <bnbbox>
      <xmin>797</xmin>
      <ymin>146</ymin>
      <xmax>857</xmax>
      <ymax>326</ymax>
    </bnbbox>
  </object>
  <object>
    <name>person</name>
    <pose>Unspecified</pose>
    <truncated>0</truncated>
    <difficult>0</difficult>
    <bnbbox>
      <xmin>1797</xmin>
      <ymin>205</ymin>
      <xmax>1863</xmax>
      <ymax>396</ymax>
    </bnbbox>
  </object>
  <object>
    <name>person</name>
    <pose>Unspecified</pose>
    <truncated>0</truncated>
    <difficult>0</difficult>
    <bnbbox>
      <xmin>1636</xmin>
      <ymin>252</ymin>
      <xmax>1702</xmax>
      <ymax>457</ymax>
    </bnbbox>
  </object>
  <object>
    <name>person</name>
    <pose>Unspecified</pose>
    <truncated>0</truncated>
    <difficult>0</difficult>
    <bnbbox>
      <xmin>418</xmin>
      <ymin>97</ymin>
      <xmax>471</xmax>
      <ymax>258</ymax>
    </bnbbox>
  </object>
  <object>
    <name>person</name>
    <pose>Unspecified</pose>
    <truncated>0</truncated>
    <difficult>0</difficult>
    <bnbbox>
      <xmin>370</xmin>
      <ymin>406</ymin>
      <xmax>448</xmax>
      <ymax>649</ymax>
    </bnbbox>
  </object>
  <object>
    <name>person</name>
    <pose>Unspecified</pose>
    <truncated>0</truncated>
    <difficult>0</difficult>
    <bnbbox>
      <xmin>631</xmin>
      <ymin>762</ymin>
      <xmax>735</xmax>
      <ymax>1014</ymax>
    </bnbbox>
  </object>
  <object>
    <name>person</name>
    <pose>Unspecified</pose>
    <truncated>0</truncated>
    <difficult>0</difficult>
    <bnbbox>
      <xmin>1485</xmin>
      <ymin>62</ymin>
      <xmax>1542</xmax>
      <ymax>218</ymax>
    </bnbbox>
  </object>
  <object>
    <name>person</name>
    <pose>Unspecified</pose>
    <truncated>0</truncated>
    <difficult>0</difficult>
    <bnbbox>
      <xmin>1360</xmin>
      <ymin>562</ymin>
      <xmax>1460</xmax>
      <ymax>818</ymax>
    </bnbbox>
  </object>
  <object>
    <name>person</name>
    <pose>Unspecified</pose>
    <truncated>0</truncated>
    <difficult>0</difficult>
    <bnbbox>
      <xmin>1104</xmin>
      <ymin>206</ymin>
      <xmax>1172</xmax>
      <ymax>396</ymax>
    </bnbbox>
  </object>
  <object>
    <name>person</name>
    <pose>Unspecified</pose>
    <truncated>0</truncated>
    <difficult>0</difficult>
    <bnbbox>
      <xmin>1725</xmin>
      <ymin>459</ymin>
      <xmax>1808</xmax>
      <ymax>669</ymax>
    </bnbbox>
  </object>
  <object>
    <name>person</name>
    <pose>Unspecified</pose>
    <truncated>0</truncated>
    <difficult>0</difficult>
    <bnbbox>
      <xmin>287</xmin>
      <ymin>133</ymin>
      <xmax>339</xmax>
      <ymax>289</ymax>
    </bnbbox>
  </object>
  <object>
    <name>person</name>
    <pose>Unspecified</pose>
    <truncated>0</truncated>
    <difficult>0</difficult>
    <bnbbox>
      <xmin>331</xmin>
      <ymin>88</ymin>
      <xmax>380</xmax>
      <ymax>262</ymax>
    </bnbbox>
  </object>
  <object>
    <name>person</name>
    <pose>Unspecified</pose>
    <truncated>0</truncated>
    <difficult>0</difficult>
    <bnbbox>
      <xmin>265</xmin>
      <ymin>89</ymin>
      <xmax>323</xmax>
      <ymax>269</ymax>
    </bnbbox>
  </object>
  <object>
    <name>person</name>
    <pose>Unspecified</pose>
    <truncated>0</truncated>
    <difficult>0</difficult>
    <bnbbox>
      <xmin>354</xmin>
      <ymin>103</ymin>
      <xmax>411</xmax>
      <ymax>285</ymax>
    </bnbbox>
  </object>
  <object>
    <name>person</name>
    <pose>Unspecified</pose>
    <truncated>0</truncated>
    <difficult>0</difficult>
    <bnbbox>
      <xmin>1559</xmin>
      <ymin>258</ymin>
      <xmax>1615</xmax>
      <ymax>440</ymax>
    </bnbbox>
  </object>
  <object>
    <name>person</name>
    <pose>Unspecified</pose>
    <truncated>0</truncated>
    <difficult>0</difficult>
    <bnbbox>
      <xmin>1199</xmin>
      <ymin>34</ymin>
      <xmax>1262</xmax>
      <ymax>145</ymax>
    </bnbbox>
  </object>
  <object>
    <name>person</name>
    <pose>Unspecified</pose>
    <truncated>0</truncated>
    <difficult>0</difficult>
    <bnbbox>
      <xmin>498</xmin>
      <ymin>137</ymin>
      <xmax>560</xmax>
      <ymax>308</ymax>
    </bnbbox>
  </object>
  <object>
    <name>person</name>
    <pose>Unspecified</pose>
    <truncated>0</truncated>
    <difficult>0</difficult>
    <bnbbox>
      <xmin>256</xmin>
      <ymin>377</ymin>
      <xmax>320</xmax>
      <ymax>589</ymax>
    </bnbbox>
  </object>
  <object>
    <name>person</name>
    <pose>Unspecified</pose>
    <truncated>0</truncated>
    <difficult>0</difficult>
    <bnbbox>
      <xmin>1419</xmin>
      <ymin>200</ymin>
      <xmax>1471</xmax>
      <ymax>370</ymax>
    </bnbbox>
  </object>
  <object>
    <name>person</name>
    <pose>Unspecified</pose>
    <truncated>0</truncated>
    <difficult>0</difficult>
    <bnbbox>
      <xmin>1446</xmin>
      <ymin>248</ymin>
      <xmax>1500</xmax>
      <ymax>420</ymax>
    </bnbbox>
  </object>
  <object>
    <name>person</name>
    <pose>Unspecified</pose>
    <truncated>0</truncated>
    <difficult>0</difficult>
    <bnbbox>
      <xmin>485</xmin>
      <ymin>36</ymin>
      <xmax>536</xmax>
      <ymax>194</ymax>
    </bnbbox>
  </object>
  <object>
    <name>person</name>
    <pose>Unspecified</pose>
    <truncated>0</truncated>
    <difficult>0</difficult>
    <bnbbox>
      <xmin>218</xmin>
      <ymin>395</ymin>
      <xmax>290</xmax>
      <ymax>597</ymax>
    </bnbbox>
  </object>
  <object>
    <name>person</name>
    <pose>Unspecified</pose>
    <truncated>0</truncated>
    <difficult>0</difficult>
    <bnbbox>
      <xmin>459</xmin>
      <ymin>83</ymin>
      <xmax>516</xmax>
      <ymax>251</ymax>
    </bnbbox>
  </object>
  <object>
    <name>person</name>
    <pose>Unspecified</pose>
    <truncated>0</truncated>
    <difficult>0</difficult>
    <bnbbox>
      <xmin>544</xmin>
      <ymin>57</ymin>
      <xmax>582</xmax>
      <ymax>223</ymax>
    </bnbbox>
  </object>
  <object>
    <name>person</name>
    <pose>Unspecified</pose>
    <truncated>0</truncated>
    <difficult>0</difficult>
    <bnbbox>
      <xmin>1213</xmin>
      <ymin>-18</ymin>
      <xmax>1279</xmax>
      <ymax>132</ymax>
    </bnbbox>
  </object>
  <object>
    <name>person</name>
    <pose>Unspecified</pose>
    <truncated>0</truncated>
    <difficult>0</difficult>
    <bnbbox>
      <xmin>880</xmin>
      <ymin>128</ymin>
      <xmax>933</xmax>
      <ymax>302</ymax>
    </bnbbox>
  </object>
  <object>
    <name>person</name>
    <pose>Unspecified</pose>
    <truncated>0</truncated>
    <difficult>0</difficult>
    <bnbbox>
      <xmin>915</xmin>
      <ymin>124</ymin>
      <xmax>970</xmax>
      <ymax>285</ymax>
    </bnbbox>
  </object>
  <object>
    <name>person</name>
    <pose>Unspecified</pose>
    <truncated>0</truncated>
    <difficult>0</difficult>
    <bnbbox>
      <xmin>532</xmin>
      <ymin>145</ymin>
      <xmax>603</xmax>
      <ymax>326</ymax>
    </bnbbox>
  </object>
  <object>
    <name>person</name>
    <pose>Unspecified</pose>
    <truncated>0</truncated>
    <difficult>0</difficult>
    <bnbbox>
      <xmin>549</xmin>
      <ymin>-48</ymin>
      <xmax>589</xmax>
      <ymax>87</ymax>
    </bnbbox>
  </object>
  <object>
    <name>person</name>
    <pose>Unspecified</pose>
    <truncated>0</truncated>
    <difficult>0</difficult>
    <bnbbox>
      <xmin>997</xmin>
      <ymin>-46</ymin>
      <xmax>1043</xmax>
      <ymax>85</ymax>
    </bnbbox>
  </object>
  <object>
    <name>person</name>
    <pose>Unspecified</pose>
    <truncated>0</truncated>
    <difficult>0</difficult>
    <bnbbox>
      <xmin>1034</xmin>
      <ymin>-38</ymin>
      <xmax>1087</xmax>
      <ymax>81</ymax>
    </bnbbox>
  </object>
  <object>
    <name>person</name>
    <pose>Unspecified</pose>
    <truncated>0</truncated>
    <difficult>0</difficult>
    <bnbbox>
      <xmin>240</xmin>
      <ymin>83</ymin>
      <xmax>289</xmax>
      <ymax>263</ymax>
    </bnbbox>
  </object>
</annotation>
