<annotation>
  <filename>100421.jpg</filename>
  <size>
    <width>1920</width>
    <height>1080</height>
    <depth>3</depth>
  </size>
  <object>
    <name>person</name>
    <pose>Unspecified</pose>
    <truncated>0</truncated>
    <difficult>0</difficult>
    <bnbbox>
      <xmin>1201</xmin>
      <ymin>294</ymin>
      <xmax>1252</xmax>
      <ymax>507</ymax>
    </bnbbox>
  </object>
  <object>
    <name>person</name>
    <pose>Unspecified</pose>
    <truncated>0</truncated>
    <difficult>0</difficult>
    <bnbbox>
      <xmin>297</xmin>
      <ymin>255</ymin>
      <xmax>487</xmax>
      <ymax>632</ymax>
    </bnbbox>
  </object>
  <object>
    <name>person</name>
    <pose>Unspecified</pose>
    <truncated>0</truncated>
    <difficult>0</difficult>
    <bnbbox>
      <xmin>860</xmin>
      <ymin>293</ymin>
      <xmax>920</xmax>
      <ymax>457</ymax>
    </bnbbox>
  </object>
  <object>
    <name>person</name>
    <pose>Unspecified</pose>
    <truncated>0</truncated>
    <difficult>0</difficult>
    <bnbbox>
      <xmin>544</xmin>
      <ymin>315</ymin>
      <xmax>588</xmax>
      <ymax>474</ymax>
    </bnbbox>
  </object>
  <object>
    <name>person</name>
    <pose>Unspecified</pose>
    <truncated>0</truncated>
    <difficult>0</difficult>
    <bnbbox>
      <xmin>629</xmin>
      <ymin>314</ymin>
      <xmax>669</xmax>
      <ymax>423</ymax>
    </bnbbox>
  </object>
  <object>
    <name>person</name>
    <pose>Unspecified</pose>
    <truncated>0</truncated>
    <difficult>0</difficult>
    <bnbbox>
      <xmin>950</xmin>
      <ymin>312</ymin>
      <xmax>1006</xmax>
      <ymax>460</ymax>
    </bnbbox>
  </object>
  <object>
    <name>person</name>
    <pose>Unspecified</pose>
    <truncated>0</truncated>
    <difficult>0</difficult>
    <bnbbox>
      <xmin>1083</xmin>
      <ymin>320</ymin>
      <xmax>1115</xmax>
      <ymax>395</ymax>
    </bnbbox>
  </object>
  <object>
    <name>person</name>
    <pose>Unspecified</pose>
    <truncated>0</truncated>
    <difficult>0</difficult>
    <bnbbox>
      <xmin>695</xmin>
      <ymin>319</ymin>
      <xmax>722</xmax>
      <ymax>391</ymax>
    </bnbbox>
  </object>
  <object>
    <name>person</name>
    <pose>Unspecified</pose>
    <truncated>0</truncated>
    <difficult>0</difficult>
    <bnbbox>
      <xmin>229</xmin>
      <ymin>309</ymin>
      <xmax>299</xmax>
      <ymax>472</ymax>
    </bnbbox>
  </object>
  <object>
    <name>person</name>
    <pose>Unspecified</pose>
    <truncated>0</truncated>
    <difficult>0</difficult>
    <bnbbox>
      <xmin>997</xmin>
      <ymin>325</ymin>
      <xmax>1025</xmax>
      <ymax>384</ymax>
    </bnbbox>
  </object>
  <object>
    <name>person</name>
    <pose>Unspecified</pose>
    <truncated>0</truncated>
    <difficult>0</difficult>
    <bnbbox>
      <xmin>1031</xmin>
      <ymin>330</ymin>
      <xmax>1049</xmax>
      <ymax>369</ymax>
    </bnbbox>
  </object>
  <object>
    <name>person</name>
    <pose>Unspecified</pose>
    <truncated>0</truncated>
    <difficult>0</difficult>
    <bnbbox>
      <xmin>730</xmin>
      <ymin>318</ymin>
      <xmax>760</xmax>
      <ymax>394</ymax>
    </bnbbox>
  </object>
  <object>
    <name>person</name>
    <pose>Unspecified</pose>
    <truncated>0</truncated>
    <difficult>0</difficult>
    <bnbbox>
      <xmin>1172</xmin>
      <ymin>304</ymin>
      <xmax>1229</xmax>
      <ymax>484</ymax>
    </bnbbox>
  </object>
</annotation>
