<annotation>
  <filename>50321.jpg</filename>
  <size>
    <width>640</width>
    <height>480</height>
    <depth>3</depth>
  </size>
  <object>
    <name>person</name>
    <pose>Unspecified</pose>
    <truncated>0</truncated>
    <difficult>0</difficult>
    <bnbbox>
      <xmin>152</xmin>
      <ymin>45</ymin>
      <xmax>352</xmax>
      <ymax>504</ymax>
    </bnbbox>
  </object>
  <object>
    <name>person</name>
    <pose>Unspecified</pose>
    <truncated>0</truncated>
    <difficult>0</difficult>
    <bnbbox>
      <xmin>45</xmin>
      <ymin>133</ymin>
      <xmax>116</xmax>
      <ymax>314</ymax>
    </bnbbox>
  </object>
  <object>
    <name>person</name>
    <pose>Unspecified</pose>
    <truncated>0</truncated>
    <difficult>0</difficult>
    <bnbbox>
      <xmin>344</xmin>
      <ymin>125</ymin>
      <xmax>442</xmax>
      <ymax>347</ymax>
    </bnbbox>
  </object>
  <object>
    <name>person</name>
    <pose>Unspecified</pose>
    <truncated>0</truncated>
    <difficult>0</difficult>
    <bnbbox>
      <xmin>453</xmin>
      <ymin>172</ymin>
      <xmax>515</xmax>
      <ymax>328</ymax>
    </bnbbox>
  </object>
  <object>
    <name>person</name>
    <pose>Unspecified</pose>
    <truncated>0</truncated>
    <difficult>0</difficult>
    <bnbbox>
      <xmin>530</xmin>
      <ymin>161</ymin>
      <xmax>574</xmax>
      <ymax>296</ymax>
    </bnbbox>
  </object>
</annotation>
