<annotation>
  <filename>90521.jpg</filename>
  <size>
    <width>1920</width>
    <height>1080</height>
    <depth>3</depth>
  </size>
  <object>
    <name>person</name>
    <pose>Unspecified</pose>
    <truncated>0</truncated>
    <difficult>0</difficult>
    <bnbbox>
      <xmin>684</xmin>
      <ymin>254</ymin>
      <xmax>919</xmax>
      <ymax>885</ymax>
    </bnbbox>
  </object>
  <object>
    <name>person</name>
    <pose>Unspecified</pose>
    <truncated>0</truncated>
    <difficult>0</difficult>
    <bnbbox>
      <xmin>1295</xmin>
      <ymin>436</ymin>
      <xmax>1390</xmax>
      <ymax>661</ymax>
    </bnbbox>
  </object>
  <object>
    <name>person</name>
    <pose>Unspecified</pose>
    <truncated>0</truncated>
    <difficult>0</difficult>
    <bnbbox>
      <xmin>1661</xmin>
      <ymin>442</ymin>
      <xmax>1729</xmax>
      <ymax>650</ymax>
    </bnbbox>
  </object>
  <object>
    <name>person</name>
    <pose>Unspecified</pose>
    <truncated>0</truncated>
    <difficult>0</difficult>
    <bnbbox>
      <xmin>1415</xmin>
      <ymin>453</ymin>
      <xmax>1491</xmax>
      <ymax>662</ymax>
    </bnbbox>
  </object>
  <object>
    <name>person</name>
    <pose>Unspecified</pose>
    <truncated>0</truncated>
    <difficult>0</difficult>
    <bnbbox>
      <xmin>1349</xmin>
      <ymin>436</ymin>
      <xmax>1449</xmax>
      <ymax>670</ymax>
    </bnbbox>
  </object>
  <object>
    <name>person</name>
    <pose>Unspecified</pose>
    <truncated>0</truncated>
    <difficult>0</difficult>
    <bnbbox>
      <xmin>1581</xmin>
      <ymin>413</ymin>
      <xmax>1690</xmax>
      <ymax>685</ymax>
    </bnbbox>
  </object>
  <object>
    <name>person</name>
    <pose>Unspecified</pose>
    <truncated>0</truncated>
    <difficult>0</difficult>
    <bnbbox>
      <xmin>1843</xmin>
      <ymin>397</ymin>
      <xmax>1934</xmax>
      <ymax>634</ymax>
    </bnbbox>
  </object>
</annotation>
